cgkit/__init__.py
cgkit/cflow/__init__.py
cgkit/cflow/basegraph.py
cgkit/cflow/basegraph_networkx.py
cgkit/cflow/cflow_dsl.py
cgkit/cflow/controller.py
cgkit/cflow/graph.py
cgkit/cflow/model_runtime.py
cgkit/cflow/model_runtime_node.py
cgkit/cflow/node.py
cgkit/cflow/utils_cflow_dsl.py
cgkit/ctree/__init__.py
cgkit/ctree/srctree.py
cgkit/fargs/__init__.py
cgkit/fargs/fargs.py
cgkit/fname/__init__.py
cgkit/fname/fname.py
cgkit/util/__init__.py
cgkit/util/test.py
code_generation_toolkit-0.2.2.dist-info/LICENSE
code_generation_toolkit-0.2.2.dist-info/METADATA
code_generation_toolkit-0.2.2.dist-info/WHEEL
code_generation_toolkit-0.2.2.dist-info/top_level.txt
code_generation_toolkit-0.2.2.dist-info/RECORD
