Metadata-Version: 2.1
Name: code-generation-toolkit
Version: 0.2.2
Summary: CG-Kit: Code Generation tool-Kit for algorithmic and performance portability
Author-email: Johann Rudi <jrudi@vt.edu>, "Aidan H. Chadha" <aidanchadha03@vt.edu>, Youngjun Lee <leey@anl.gov>
License: GNU GENERAL PUBLIC LICENSE
Keywords: code generation,algorithmic portability,performance portability
Classifier: Development Status :: 4 - Beta
Classifier: Intended Audience :: Developers
Classifier: Intended Audience :: Science/Research
Classifier: License :: OSI Approved :: GNU General Public License v3 (GPLv3)
Classifier: Operating System :: OS Independent
Classifier: Programming Language :: Python
Classifier: Programming Language :: Python :: 3
Classifier: Programming Language :: Python :: 3.8
Classifier: Programming Language :: Python :: 3.9
Classifier: Programming Language :: Python :: 3.10
Requires-Python: >=3.8
License-File: LICENSE
Requires-Dist: matplotlib >=3.6
Requires-Dist: networkx >=2.7
Requires-Dist: numpy >=1.22
Requires-Dist: pathlib >=1.0.1
Provides-Extra: ctree-all
Requires-Dist: mako >=1.2 ; extra == 'ctree-all'
Requires-Dist: ct3 >=3.2 ; extra == 'ctree-all'
Provides-Extra: ctree-cheetah3
Requires-Dist: ct3 >=3.2 ; extra == 'ctree-cheetah3'
Provides-Extra: ctree-mako
Requires-Dist: mako >=1.2 ; extra == 'ctree-mako'
Provides-Extra: dev
Requires-Dist: build ; extra == 'dev'
Requires-Dist: bumpver ; extra == 'dev'
Requires-Dist: pip-tools ; extra == 'dev'
Requires-Dist: pytest ; extra == 'dev'
Requires-Dist: twine ; extra == 'dev'
Provides-Extra: fargs
Requires-Dist: horast ; extra == 'fargs'
Requires-Dist: transpyle ; extra == 'fargs'
Requires-Dist: typed-ast ; extra == 'fargs'
